pendingai/__init__.py
pendingai/__main__.py
pendingai/abc.py
pendingai/api_resources/interfaces.py
pendingai/api_resources/object.py
pendingai/api_resources/parser.py
pendingai/api_resources/validator.py
pendingai/auth/__init__.py
pendingai/auth/controller.py
pendingai/auth/session.py
pendingai/auth/session_claims.py
pendingai/auth/session_token.py
pendingai/cli/auth.py
pendingai/cli/commands/__init__.py
pendingai/cli/commands/generator/__init__.py
pendingai/cli/commands/generator/list_models.py
pendingai/cli/commands/generator/sample.py
pendingai/cli/commands/retrosynthesis/__init__.py
pendingai/cli/commands/retrosynthesis/create.py
pendingai/cli/commands/retrosynthesis/create_batch.py
pendingai/cli/commands/retrosynthesis/delete.py
pendingai/cli/commands/retrosynthesis/delete_batch.py
pendingai/cli/commands/retrosynthesis/export.py
pendingai/cli/commands/retrosynthesis/export_batch.py
pendingai/cli/commands/retrosynthesis/list.py
pendingai/cli/commands/retrosynthesis/list_batches.py
pendingai/cli/commands/retrosynthesis/list_engines.py
pendingai/cli/commands/retrosynthesis/list_libraries.py
pendingai/cli/commands/retrosynthesis/status.py
pendingai/cli/console.py
pendingai/cli/constants.py
pendingai/cli/context.py
pendingai/cli/parameters/__init__.py
pendingai/cli/parameters/generator.py
pendingai/cli/parameters/retrosynthesis.py
pendingai/cli/renderables/__init__.py
pendingai/cli/renderables/generator.py
pendingai/cli/renderables/retrosynthesis.py
pendingai/cli/shared.py
pendingai/cli/utils/generate_html.py
pendingai/client.py
pendingai/config.py
pendingai/constants.py
pendingai/exceptions.py
pendingai/html_templates/__init__.py
pendingai/html_templates/css/style.css
pendingai/html_templates/job_template.html
pendingai/html_templates/jobs_overview_template.html
pendingai/html_templates/route_template.html
pendingai/html_templates/scripts/cytoscape.min.js
pendingai/html_templates/scripts/date_formatter.js
pendingai/html_templates/scripts/route_viewer.js
pendingai-0.5.5.dist-info/METADATA
pendingai-0.5.5.dist-info/WHEEL
pendingai-0.5.5.dist-info/entry_points.txt
pendingai-0.5.5.dist-info/licenses/LICENSE
pendingai-0.5.5.dist-info/RECORD
