Metadata-Version: 2.4
Name: pendingai
Version: 0.5.5
Summary: Python SDK and CLI for the Pending AI API
License: MIT
License-File: LICENSE
Author: Pending AI
Author-email: support@pending.ai
Maintainer: Pending AI
Maintainer-email: support@pending.ai
Requires-Python: >=3.10.0,<4.0.0
Classifier: License :: OSI Approved :: MIT License
Classifier: Programming Language :: Python :: 3
Classifier: Programming Language :: Python :: 3.10
Classifier: Programming Language :: Python :: 3.11
Classifier: Programming Language :: Python :: 3.12
Classifier: Programming Language :: Python :: 3.13
Classifier: Programming Language :: Python :: 3.14
Requires-Dist: jinja2 (>=3.1.6,<4.0.0)
Requires-Dist: lxml (>=6.0.0,<7.0.0)
Requires-Dist: pyjwt (>=2.10.1,<3.0.0)
Requires-Dist: pyyaml (>=6.0.3,<7.0.0)
Requires-Dist: rdkit (>=2025.3.5,<2026.0.0)
Requires-Dist: requests (>=2.32.3,<3.0.0)
Requires-Dist: typer (>=0.15.1,<0.22.0)
Project-URL: Documentation, https://docs.pending.ai
Project-URL: Homepage, https://pending.ai
